__init__.py
dictpath.py
simple_dictpath-1.0.3.dist-info/LICENSE
simple_dictpath-1.0.3.dist-info/METADATA
simple_dictpath-1.0.3.dist-info/WHEEL
simple_dictpath-1.0.3.dist-info/top_level.txt
simple_dictpath-1.0.3.dist-info/RECORD
