Metadata-Version: 2.1
Name: simple-dictpath
Version: 1.0.3
Summary: Provides path-like access to nested dictionary elements
Author-email: "path.to.file" <python@tofile.dev>
Project-URL: Homepage, https://github.com/pathtofile/dictpath
Project-URL: Bug Tracker, https://github.com/pathtofile/dictpath/issues
Classifier: Programming Language :: Python :: 3
Classifier: License :: OSI Approved :: MIT License
Classifier: Operating System :: OS Independent
Requires-Python: >=3.10
License-File: LICENSE
